setup.py
bodiesrun/__init__.py
bodiesrun.egg-info/PKG-INFO
bodiesrun.egg-info/SOURCES.txt
bodiesrun.egg-info/dependency_links.txt
bodiesrun.egg-info/top_level.txt