Metadata-Version: 2.1
Name: bodiesrun
Version: 2.0.0
Summary: run the threebodies
Author: Riming
Author-email: dhjfirst@hotmail.com
License: apache 3.0
Requires: numpy
